{"MAXAirDeviceList":[{"Channel":"L1","ID":"100","PowerStatus":"OFF","PresetTemperature":"26C","IndoorTemperature":"18C","FanSpeed":"Low","Selection":"Cool"},{"Channel":"L1","ID":"101","PowerStatus":"ON","PresetTemperature":"24C","IndoorTemperature":"18C","FanSpeed":"Auto","Selection":"Fan"},{"Channel":"L1","ID":"102","PowerStatus":"OFF","PresetTemperature":"31C","IndoorTemperature":"24C","FanSpeed":"Top","Selection":"Cool"},{"Channel":"L1","ID":"103","PowerStatus":"OFF","PresetTemperature":"31C","IndoorTemperature":"19C","FanSpeed":"Low","Selection":"Heat"},{"Channel":"L1","ID":"104","PowerStatus":"OFF","PresetTemperature":"27C","IndoorTemperature":"29C","FanSpeed":"Top","Selection":"Auto"},{"Channel":"L1","ID":"105","PowerStatus":"OFF","PresetTemperature":"22C","IndoorTemperature":"21C","FanSpeed":"High","Selection":"Dry"},{"Channel":"L1","ID":"106","PowerStatus":"OFF","PresetTemperature":"30C","IndoorTemperature":"26C","FanSpeed":"Low","Selection":"Cool"},{"Channel":"L1","ID":"107","PowerStatus":"ON","PresetTemperature":"17C","IndoorTemperature":"26C","FanSpeed":"High","Selection":"Fan"},{"Channel":"L1","ID":"108","PowerStatus":"OFF","PresetTemperature":"21C","IndoorTemperature":"17C","FanSpeed":"Top","Selection":"Dry"},{"Channel":"L1","ID":"109","PowerStatus":"OFF","PresetTemperature":"17C","IndoorTemperature":"21C","FanSpeed":"Med","Selection":"Cool"}]}